pytest_nginx/__init__.py
pytest_nginx/factories.py
pytest_nginx/plugin.py
pytest_nginx/templates.py
pytest_nginx_iplweb-1.1.1.dist-info/LICENSE
pytest_nginx_iplweb-1.1.1.dist-info/METADATA
pytest_nginx_iplweb-1.1.1.dist-info/WHEEL
pytest_nginx_iplweb-1.1.1.dist-info/entry_points.txt
pytest_nginx_iplweb-1.1.1.dist-info/top_level.txt
pytest_nginx_iplweb-1.1.1.dist-info/RECORD
