Metadata-Version: 2.1
Name: pytest-nginx-iplweb
Version: 1.1.1
Summary: nginx fixture for pytest - iplweb temporary fork
Home-page: https://github.com/mpasternak/pytest-nginx
Author: Jakub Klinkovský and Michał Pasternak
Author-email: michal.dtz+pytestnginx@gmail.com
License: GPLv3
Keywords: tests py.test pytest fixture nginx
Platform: UNKNOWN
Classifier: Development Status :: 5 - Production/Stable
Classifier: Environment :: Web Environment
Classifier: Intended Audience :: Developers
Classifier: License :: OSI Approved :: GNU General Public License v3 (GPLv3)
Classifier: Natural Language :: English
Classifier: Operating System :: OS Independent
Classifier: Programming Language :: Python
Classifier: Programming Language :: Python :: 3
Classifier: Topic :: Software Development :: Libraries :: Python Modules
Requires-Dist: pytest (>=3.0.0)
